mecode/__init__.py
mecode/footer.txt
mecode/header.txt
mecode/main.py
mecode/matrix.py
mecode/printer.py
mecode/profilometer_parse.py
mecode/utils.py
mecode/devices/__init__.py
mecode/devices/base_serial_device.py
mecode/devices/efd_pico_pulse.py
mecode/devices/efd_pressure_box.py
mecode/devices/keyence_line_scanner.py
mecode/devices/keyence_micrometer.py
mecode/devices/keyence_profilometer.py
mecode-0.4.1.dist-info/LICENSE
mecode-0.4.1.dist-info/METADATA
mecode-0.4.1.dist-info/WHEEL
mecode-0.4.1.dist-info/top_level.txt
mecode-0.4.1.dist-info/RECORD
