Metadata-Version: 2.1
Name: mecode
Version: 0.4.1
Summary: Simple GCode generator
Home-page: https://github.com/jminardi/mecode
Author: Jack Minardi
Author-email: jack@minardi.org
License: UNKNOWN
Download-URL: https://github.com/jminardi/mecode/tarball/master
Keywords: gcode,3dprinting,cnc,reprap,additive
Platform: UNKNOWN
Requires-Dist: pyserial
Requires-Dist: numpy
